odoo/addons/invoice_somconnexio/CHANGELOG.md
odoo/addons/invoice_somconnexio/README.rst
odoo/addons/invoice_somconnexio/__init__.py
odoo/addons/invoice_somconnexio/__manifest__.py
odoo/addons/invoice_somconnexio/backblaze/__init__.py
odoo/addons/invoice_somconnexio/backblaze/b2_service.py
odoo/addons/invoice_somconnexio/controllers/__init__.py
odoo/addons/invoice_somconnexio/controllers/user_controller.py
odoo/addons/invoice_somconnexio/data/account_journal.xml
odoo/addons/invoice_somconnexio/demo/invoice.xml
odoo/addons/invoice_somconnexio/listeners/__init__.py
odoo/addons/invoice_somconnexio/listeners/account_invoice.py
odoo/addons/invoice_somconnexio/models/__init__.py
odoo/addons/invoice_somconnexio/models/account_invoice.py
odoo/addons/invoice_somconnexio/models/account_invoice_line.py
odoo/addons/invoice_somconnexio/models/account_payment_order.py
odoo/addons/invoice_somconnexio/models/contract.py
odoo/addons/invoice_somconnexio/models/contract_account_invoice_line_relation.py
odoo/addons/invoice_somconnexio/models/download_invoice.py
odoo/addons/invoice_somconnexio/models/payment_return.py
odoo/addons/invoice_somconnexio/models/payment_return_line.py
odoo/addons/invoice_somconnexio/models/res_company.py
odoo/addons/invoice_somconnexio/models/send_tokenized_invoice.py
odoo/addons/invoice_somconnexio/security/ir.model.access.csv
odoo/addons/invoice_somconnexio/services/__init__.py
odoo/addons/invoice_somconnexio/services/account_invoice_process.py
odoo/addons/invoice_somconnexio/services/account_invoice_service.py
odoo/addons/invoice_somconnexio/services/schemas.py
odoo/addons/invoice_somconnexio/tests/__init__.py
odoo/addons/invoice_somconnexio/tests/backblaze/test_b2_service.py
odoo/addons/invoice_somconnexio/tests/listeners/__init__.py
odoo/addons/invoice_somconnexio/tests/listeners/test_account_invoice_listener.py
odoo/addons/invoice_somconnexio/tests/models/__init__.py
odoo/addons/invoice_somconnexio/tests/models/test_account_invoice.py
odoo_addon_invoice_somconnexio-16.0.1.0.3.dist-info/METADATA
odoo_addon_invoice_somconnexio-16.0.1.0.3.dist-info/WHEEL
odoo_addon_invoice_somconnexio-16.0.1.0.3.dist-info/top_level.txt
odoo_addon_invoice_somconnexio-16.0.1.0.3.dist-info/RECORD
