Metadata-Version: 2.1
Name: odoo-addon-invoice-somconnexio
Version: 16.0.1.0.3
Summary: invoice Som Connexió module
Home-page: https://coopdevs.org
Author: Coopdevs Treball SCCL, Som Connexió SCCL
License: AGPL-3
Platform: UNKNOWN
Classifier: Programming Language :: Python
Classifier: Framework :: Odoo
Classifier: Framework :: Odoo :: 16.0
Classifier: License :: OSI Approved :: GNU Affero General Public License v3
Requires-Python: >=3.10
Requires-Dist: b2sdk ==2.5.0
Requires-Dist: bi-sc-client
Requires-Dist: odoo-addon-account-payment-order <16.1dev,>=16.0dev
Requires-Dist: odoo-addon-account-payment-partner <16.1dev,>=16.0dev
Requires-Dist: odoo-addon-base-rest <16.1dev,>=16.0dev
Requires-Dist: odoo-addon-contract-group-somconnexio <16.1dev,>=16.0dev
Requires-Dist: odoo-addon-cooperator-somconnexio <16.1dev,>=16.0dev
Requires-Dist: odoo-addon-queue-job <16.1dev,>=16.0dev
Requires-Dist: odoo-addon-somconnexio <16.1dev,>=16.0dev
Requires-Dist: odoo <16.1dev,>=16.0a
Requires-Dist: pyopencell ==0.4.9
